squad/VERSION
squad/__init__.py
squad/__main__.py
squad/access_token.py
squad/common.py
squad/environment.py
squad/squad.py
squad/widgets/__init__.py
squad/widgets/env.py
squad/widgets/info.py
squad/widgets/logo.py
squad/widgets/topic.py
squad/widgets/topics/__init__.py
squad/widgets/topics/assets.py
squad/widgets/topics/base.py
squad/widgets/topics/datasets.py
squad/widgets/topics/defined_exchange_rates.py
squad/widgets/topics/instances.py
squad/widgets/topics/merchants.py
squad/widgets/topics/personal_units.py
squad/widgets/topics/products.py
squad/widgets/topics/projects.py
squad/widgets/topics/service_errors.py
squad/widgets/topics/tasks.py
squad/widgets/topics/undefined_exchange_rates.py
squad/widgets/topics/units.py
im_squad-1.0.2.dist-info/LICENSE
im_squad-1.0.2.dist-info/METADATA
im_squad-1.0.2.dist-info/WHEEL
im_squad-1.0.2.dist-info/entry_points.txt
im_squad-1.0.2.dist-info/top_level.txt
im_squad-1.0.2.dist-info/RECORD
