Metadata-Version: 2.1
Name: im-squad
Version: 1.0.2
Summary: The IM Squonk2 Admin Text-based UI (SquAd)
Home-page: https://github.com/informaticsmatters/squonk2-admin
Author: Alan Christie
Author-email: achristie@informaticsmatters.com
License: MIT
Keywords: configuration
Platform: any
Classifier: Development Status :: 5 - Production/Stable
Classifier: Environment :: Console
Classifier: Intended Audience :: Developers
Classifier: License :: OSI Approved :: MIT License
Classifier: Programming Language :: Python :: 3.10
Classifier: Topic :: System :: Installation/Setup
Classifier: Operating System :: POSIX :: Linux
License-File: LICENSE
Requires-Dist: humanize (~=4.3.0)
Requires-Dist: im-squonk2-client (<2.0.0,>=1.13.1)
Requires-Dist: pandas (~=1.4.0)
Requires-Dist: pyyaml (~=6.0)
Requires-Dist: textual (==0.1.18)
